pyphys/__init__.py
pyphys-0.0.1.dist-info/METADATA
pyphys-0.0.1.dist-info/RECORD
pyphys-0.0.1.dist-info/WHEEL
pyphys-0.0.1.dist-info/top_level.txt
