Metadata-Version: 2.1
Name: pyphys
Version: 0.0.1
Summary: pygame based physics engine for better 2D simulations
Home-page: https://github.com/oxhagolli/pyphys
Author: Orens Xhagolli
Author-email: orens.xhagolli@hotmail.com
License: UNKNOWN
Platform: UNKNOWN
Classifier: Programming Language :: Python :: 3
Classifier: License :: OSI Approved :: MIT License
Classifier: Operating System :: OS Independent
